genomix/__init__.py
genomix/apps.py
genomix/fields.py
genomix/filters.py
genomix/models.py
genomix/querysets.py
genomix/routers.py
genomix/test.py
genomix/utils.py
django_genomix-1.1.0.dist-info/AUTHORS.rst
django_genomix-1.1.0.dist-info/LICENSE
django_genomix-1.1.0.dist-info/METADATA
django_genomix-1.1.0.dist-info/WHEEL
django_genomix-1.1.0.dist-info/top_level.txt
django_genomix-1.1.0.dist-info/RECORD
